gemini_parser/__init__.py
gemini_parser/caching.py
gemini_parser/document_processor.py
gemini_parser/file_manager.py
gemini_parser/utils.py
gemini_parser-0.1.0.post2.dist-info/METADATA
gemini_parser-0.1.0.post2.dist-info/WHEEL
gemini_parser-0.1.0.post2.dist-info/entry_points.txt
gemini_parser-0.1.0.post2.dist-info/top_level.txt
gemini_parser-0.1.0.post2.dist-info/RECORD
