Metadata-Version: 2.1
Name: gemini-parser
Version: 0.1.0.post2
Summary: A Python library for processing documents with the Gemini API
Home-page: https://github.com/timnirmal/gemini-parser
Author: Thimira Nirmal
Author-email: Thimira Nirmal <timnirmal@gmail.com>
License: MIT
Project-URL: Homepage, https://github.com/timnirmal/gemini-parser
Project-URL: Repository, https://github.com/timnirmal/gemini-parser
Classifier: Programming Language :: Python :: 3
Classifier: License :: OSI Approved :: MIT License
Classifier: Operating System :: OS Independent
Requires-Python: >=3.8
Requires-Dist: tqdm
Requires-Dist: PyPDF2
Requires-Dist: google-genai
Requires-Dist: python-dotenv
Requires-Dist: httpx
